example_configs/config.json
gbf_beautify_honors/__init__.py
gbf_beautify_honors/action.py
gbf_beautify_honors/config.json
gbf_beautify_honors/exception.py
gbf_beautify_honors/main.py
gbf_beautify_honors/solver.py
gbf_beautify_honors-0.1.3.dist-info/entry_points.txt
gbf_beautify_honors-0.1.3.dist-info/LICENSE
gbf_beautify_honors-0.1.3.dist-info/WHEEL
gbf_beautify_honors-0.1.3.dist-info/METADATA
gbf_beautify_honors-0.1.3.dist-info/RECORD
