Metadata-Version: 2.1
Name: gbf-beautify-honors
Version: 0.1.3
Summary: A CLI tool to help you figure out how to beautify honors in the Guild War event.
Home-page: https://github.com/qq88976321/gbf-beautify-honors
License: MIT
Keywords: gbf,grandblue fantasy
Author: qq88976321
Author-email: qq88976321@gmail.com
Requires-Python: >=3.7,<4.0
Classifier: Development Status :: 4 - Beta
Classifier: License :: OSI Approved :: MIT License
Classifier: Programming Language :: Python :: 3
Classifier: Programming Language :: Python :: 3.10
Classifier: Programming Language :: Python :: 3.7
Classifier: Programming Language :: Python :: 3.8
Classifier: Programming Language :: Python :: 3.9
Classifier: Topic :: Games/Entertainment :: Role-Playing
Requires-Dist: click (>=8.0.3,<9.0.0)
Requires-Dist: dataclasses-json (>=0.5.7,<0.6.0)
Requires-Dist: ortools (>=9.3.10497,<10.0.0)
Requires-Dist: tabulate (>=0.8.9,<0.9.0)
Requires-Dist: types-setuptools (>=57.4.14,<58.0.0)
Requires-Dist: types-tabulate (>=0.8.8,<0.9.0)
Requires-Dist: wcwidth (>=0.2.5,<0.3.0)
Project-URL: Repository, https://github.com/qq88976321/gbf-beautify-honors
